Metadata-Version: 2.1
Name: swindpy
Version: 0.0.5
Summary: Package to analyze magnetic storm phenomena.
Home-page: https://github.com/adelarja/space_weather
Author: 
Author-email: 
License: BSD 3-Clause License
Keywords: solar,wind,space weather,swindpy,magnetic cloud
Platform: UNKNOWN
Classifier: Development Status :: 1 - Planning
Classifier: Intended Audience :: Education
Classifier: Intended Audience :: Science/Research
Classifier: License :: OSI Approved :: BSD License
Classifier: Operating System :: OS Independent
Classifier: Programming Language :: Python
Classifier: Programming Language :: Python :: 3.9
Classifier: Programming Language :: Python :: Implementation :: CPython
Classifier: Topic :: Scientific/Engineering
License-File: LICENSE
